genconf_script/__init__.py
genconf_script-0.0.2.dist-info/LICENSE.txt
genconf_script-0.0.2.dist-info/METADATA
genconf_script-0.0.2.dist-info/WHEEL
genconf_script-0.0.2.dist-info/top_level.txt
genconf_script-0.0.2.dist-info/RECORD
